pyxie/__init__.py
the_pyxie-0.1.1.dist-info/LICENSE
the_pyxie-0.1.1.dist-info/WHEEL
the_pyxie-0.1.1.dist-info/METADATA
the_pyxie-0.1.1.dist-info/RECORD
